artfullylondon/ingestschema/__init__.py
artfullylondon/ingestschema/basic-types.json
artfullylondon/ingestschema/event.json
artfullylondon/ingestschema/feed-entity-watch.json
artfullylondon/ingestschema/feed-entity.json
artfullylondon/ingestschema/feed-event.json
artfullylondon/ingestschema/image-types.json
artfullylondon/ingestschema/rules-types.json
artfullylondon/ingestschema/venue-status.json
artfullylondon/ingestschema/venue.json
artfullylondon_ingestschema-2.1.0.dist-info/LICENSE
artfullylondon_ingestschema-2.1.0.dist-info/METADATA
artfullylondon_ingestschema-2.1.0.dist-info/WHEEL
artfullylondon_ingestschema-2.1.0.dist-info/top_level.txt
artfullylondon_ingestschema-2.1.0.dist-info/RECORD
