Metadata-Version: 2.1
Name: artfullylondon-ingestschema
Version: 2.1.0
Summary: Domain schema for Artfully London ingest system
Home-page: UNKNOWN
Author: Steve Johns
Author-email: steve@stevejay.net
License: MIT License
Platform: UNKNOWN
Requires-Python: >=3.7
